dagprep/__init__.py
dagprep/core/__init__.py
dagprep/core/base/__init__.py
dagprep/core/base/data_source.py
dagprep/core/base/transformation.py
dagprep/core/explorer/__init__.py
dagprep/core/explorer/action_fn.py
dagprep/core/explorer/counter_value.py
dagprep/core/explorer/pipeline_explorer.py
dagprep/core/pipeline.py
dagprep/resources/logging.conf
dagprep/utils/__init__.py
dagprep/utils/find_data_sources.py
dagprep-1.0.0.dist-info/METADATA
dagprep-1.0.0.dist-info/WHEEL
dagprep-1.0.0.dist-info/RECORD
