Metadata-Version: 2.1
Name: dagprep
Version: 1.0.0
Summary: 
Author: Giuseppe Ambrosio
Author-email: giuambro97@gmail.com
Requires-Python: >=3.8,<4.0
Classifier: Programming Language :: Python :: 3
Classifier: Programming Language :: Python :: 3.8
Classifier: Programming Language :: Python :: 3.9
Classifier: Programming Language :: Python :: 3.10
Classifier: Programming Language :: Python :: 3.11
Requires-Dist: graphviz (>=0.20.1,<0.21.0)
Requires-Dist: matplotlib (>=3.7.2,<4.0.0)
Requires-Dist: networkx (>=3.1,<4.0)
